django_wecom/__init__.py
django_wecom/admin.py
django_wecom/apps.py
django_wecom/context_processors.py
django_wecom/forms.py
django_wecom/models.py
django_wecom/urls.py
django_wecom/views.py
django_wecom/migrations/0001_initial.py
django_wecom/migrations/__init__.py
django_wecom-1.3.dist-info/licenses/LICENSE
django_wecom-1.3.dist-info/METADATA
django_wecom-1.3.dist-info/WHEEL
django_wecom-1.3.dist-info/top_level.txt
django_wecom-1.3.dist-info/RECORD
