Metadata-Version: 2.4
Name: django_wecom
Version: 1.3
Summary: Wecom Auth for Django
Author-email: Edgar Liu <liuzihao@qdzx.net.cn>
License: MIT
Project-URL: Homepage, https://github.com/liuzihaohao/django_wecom
Requires-Python: >=3.8
License-File: LICENSE
Requires-Dist: requests
Dynamic: license-file
